bazinBlackBody/BBBCore.py
bazinBlackBody/BBBEngine.py
bazinBlackBody/__init__.py
bazinBlackBody/__version__.py
BazinBlackBody-0.7.dist-info/LICENSE
BazinBlackBody-0.7.dist-info/METADATA
BazinBlackBody-0.7.dist-info/WHEEL
BazinBlackBody-0.7.dist-info/top_level.txt
BazinBlackBody-0.7.dist-info/RECORD
