Metadata-Version: 2.1
Name: BazinBlackBody
Version: 0.7
Summary: Fitting multiband lightcurves with a Bazin-Blackbody surface
Home-page: https://github.com/RoyWilliams/bazinBlackBody
Author: RoyDavidWilliams
Author-email: roydavidwilliams@gmail.com
License: MIT
Classifier: Development Status :: 4 - Beta
Classifier: License :: OSI Approved :: MIT License
Classifier: Programming Language :: Python :: 3.6
Classifier: Topic :: Utilities
Requires-Python: >=3.6
License-File: LICENSE
Requires-Dist: numpy
Requires-Dist: scipy
Requires-Dist: matplotlib
